sphinxlinter.py
sphinx_linter-0.1.5.dist-info/licenses/LICENSE
sphinx_linter-0.1.5.dist-info/METADATA
sphinx_linter-0.1.5.dist-info/WHEEL
sphinx_linter-0.1.5.dist-info/entry_points.txt
sphinx_linter-0.1.5.dist-info/top_level.txt
sphinx_linter-0.1.5.dist-info/RECORD
