Metadata-Version: 2.4
Name: sphinx-linter
Version: 0.1.5
Summary: A lightweight Python linter for checking Sphinx docstrings.
Author-email: rmoralespp <rmoralespp@gmail.com>
Project-URL: Source, https://github.com/rmoralespp/sphinxlinter
Project-URL: Homepage, https://github.com/rmoralespp/sphinxlinter
Project-URL: Changelog, https://github.com/rmoralespp/sphinxlinter/blob/main/CHANGELOG.md
Project-URL: Issues, https://github.com/rmoralespp/sphinxlinter/issues
Keywords: python,documentation,linter,developer-tools,code-quality,docstrings
Classifier: Programming Language :: Python
Classifier: Programming Language :: Python :: 3 :: Only
Classifier: Programming Language :: Python :: 3.9
Classifier: Programming Language :: Python :: 3.10
Classifier: Programming Language :: Python :: 3.11
Classifier: Programming Language :: Python :: 3.12
Classifier: Programming Language :: Python :: 3.13
Classifier: Programming Language :: Python :: 3.14
Classifier: Intended Audience :: Developers
Classifier: Intended Audience :: Information Technology
Classifier: Topic :: Software Development :: Libraries :: Python Modules
Classifier: Topic :: Internet
Classifier: Topic :: Utilities
Classifier: Topic :: Documentation
Classifier: Topic :: Software Development :: Quality Assurance
Requires-Python: >=3.9
License-File: LICENSE
Dynamic: license-file
